{"filename": "mglkhopat_64_2022-12-11T10-12-00+0530.jpg", "timestamp": "2022-12-12 17:14:54.209314", "camera_id": null, "results": [{"box": {"xmin": 1368, "ymin": 454, "xmax": 1415, "ymax": 482}, "plate": "mh04jh6120", "region": {"code": "in", "score": 0.946}, "score": 0.9, "candidates": [{"score": 0.9, "plate": "mh04jh6120"}], "dscore": 0.448, "vehicle": {"score": 0.339, "type": "Big Truck", "box": {"xmin": 1043, "ymin": 60, "xmax": 1488, "ymax": 571}}}], "usage": {"calls": 78758, "max_calls": 500000}, "processing_time": 166.671}