{"filename": "mglkhopat_65_2022-12-11T13-19-00+0530.jpg", "timestamp": "2022-12-12 17:19:12.076836", "camera_id": null, "results": [{"box": {"xmin": 1156, "ymin": 794, "xmax": 1233, "ymax": 818}, "plate": "mh04gm6833", "region": {"code": "in", "score": 0.9}, "score": 0.877, "candidates": [{"score": 0.877, "plate": "mh04gm6833"}, {"score": 0.83, "plate": "mh04gm6839"}], "dscore": 0.848, "vehicle": {"score": 0.459, "type": "Sedan", "box": {"xmin": 1022, "ymin": 507, "xmax": 1426, "ymax": 863}}}, {"box": {"xmin": 2112, "ymin": 838, "xmax": 2227, "ymax": 874}, "plate": "mh01ma1937", "region": {"code": "in", "score": 0.842}, "score": 0.902, "candidates": [{"score": 0.902, "plate": "mh01ma1937"}, {"score": 0.818, "plate": "mh01mai937"}, {"score": 0.816, "plate": "mh0ima1937"}], "dscore": 0.762, "vehicle": {"score": 0.573, "type": "Sedan", "box": {"xmin": 1780, "ymin": 613, "xmax": 2343, "ymax": 1010}}}, {"box": {"xmin": 559, "ymin": 829, "xmax": 662, "ymax": 864}, "plate": "mh04jm7069", "region": {"code": "in", "score": 0.892}, "score": 0.9, "candidates": [{"score": 0.9, "plate": "mh04jm7069"}], "dscore": 0.532, "vehicle": {"score": 0.51, "type": "Sedan", "box": {"xmin": 435, "ymin": 484, "xmax": 996, "ymax": 943}}}], "usage": {"calls": 79271, "max_calls": 500000}, "processing_time": 124.42}